weasel_data_sources/__init__.py
weasel_data_sources/mapping/__init__.py
weasel_data_sources/mapping/mapping.py
weasel_data_sources/mapping/sources.py
weasel_data_sources/releases.py
weasel_data_sources/utils.py
weasel_data_sources/vulnerabilities.py
weasel_data_sources-2.3.0.dist-info/WHEEL
weasel_data_sources-2.3.0.dist-info/METADATA
weasel_data_sources-2.3.0.dist-info/RECORD
