Metadata-Version: 2.1
Name: weasel-data-sources
Version: 2.3.0
Summary: `weasel-data-sources` is a collection of data sources to retrieve information about software releases and vulnerabilities.
Author: Christopher Schmidt
Author-email: schmidtc@cs.uni-bonn.de
Requires-Python: >=3.6,<4.0
Classifier: Programming Language :: Python :: 3
Classifier: Programming Language :: Python :: 3.6
Classifier: Programming Language :: Python :: 3.7
Classifier: Programming Language :: Python :: 3.8
Classifier: Programming Language :: Python :: 3.9
Requires-Dist: GitPython (>=3.1.12,<4.0.0)
Requires-Dist: requests (>=2.25.1,<3.0.0)
Requires-Dist: ssdeep (>=3.4,<4.0)
Requires-Dist: svn (>=1.0.1,<2.0.0)
